MANIFEST.in
setup.py
normalization/__init__.py
normalization.egg-info/PKG-INFO
normalization.egg-info/SOURCES.txt
normalization.egg-info/dependency_links.txt
normalization.egg-info/not-zip-safe
normalization.egg-info/top_level.txt
normalization/data/abbreviations.txt
normalization/data/british.txt
normalization/data/contractions.txt
normalization/data/spellfix.txt