Metadata-Version: 1.0
Name: normalization
Version: 0.4
Summary: Text normalization module for natural language processing
Home-page: http://github.com/dchang16/text_normalization
Author: David Chang
Author-email: d26chang@gmail.com
License: MIT
Platform: UNKNOWN
